helga_reviews
